textual_serve/__init__.py
textual_serve/app_service.py
textual_serve/py.typed
textual_serve/server.py
textual_serve/static/index.html
textual_serve/static/css/xterm.css
textual_serve/static/fonts/RobotoMono-Italic-VariableFont_wght.ttf
textual_serve/static/fonts/RobotoMono-VariableFont_wght.ttf
textual_serve/static/images/background.png
textual_serve/static/js/textual.js
textual_serve/templates/app_index.html
textual_serve-1.0.3.dist-info/METADATA
textual_serve-1.0.3.dist-info/WHEEL
textual_serve-1.0.3.dist-info/licenses/LICENSE
textual_serve-1.0.3.dist-info/RECORD
