Metadata-Version: 2.3
Name: textual-serve
Version: 1.0.3
Summary: Turn your Textual TUIs in to web applications
Author-email: Will McGugan <will@textualize.io>
License-File: LICENSE
Requires-Python: >=3.8
Requires-Dist: aiohttp-jinja2>=1.6
Requires-Dist: aiohttp>=3.9.5
Requires-Dist: jinja2>=3.1.4
Requires-Dist: textual>=0.66.0
